tests/__init__.py
tests/test_commandline.py
tests/test_listfixers.py
yamlfixer/__init__.py
yamlfixer/__main__.py
yamlfixer/common.py
yamlfixer/constants.py
yamlfixer/filefixer.py
yamlfixer/problemfixer.py
yamlfixer/yamlfixer.py
yamlfixer_opt_nc-0.9.15.dist-info/LICENSE
yamlfixer_opt_nc-0.9.15.dist-info/METADATA
yamlfixer_opt_nc-0.9.15.dist-info/WHEEL
yamlfixer_opt_nc-0.9.15.dist-info/entry_points.txt
yamlfixer_opt_nc-0.9.15.dist-info/top_level.txt
yamlfixer_opt_nc-0.9.15.dist-info/RECORD
