Metadata-Version: 2.1
Name: yamlfixer-opt-nc
Version: 0.9.15
Summary: automates the fixing of problems reported by yamllint
Home-page: https://github.com/opt-nc/yamlfixer
Author: "OPT-NC"
Author-email: "jerome.alet@opt.nc"
License: "GPLv3+"
Project-URL: Bug Tracker, https://github.com/opt-nc/yamlfixer/issues
Project-URL: GitHub Releases, https://github.com/opt-nc/yamlfixer/releases
Project-URL: Files, https://pypi.org/project/yamlfixer-opt-nc/#files
Classifier: Programming Language :: Python :: 3
Classifier: License :: OSI Approved :: GNU General Public License v3 or later (GPLv3+)
Classifier: Operating System :: OS Independent
Classifier: Environment :: Console
Classifier: Topic :: Utilities
Classifier: Topic :: Text Processing
Classifier: Development Status :: 5 - Production/Stable
Classifier: Intended Audience :: System Administrators
Classifier: Intended Audience :: Developers
Classifier: Natural Language :: English
Requires-Python: >=3.6
License-File: LICENSE
Requires-Dist: yamllint (>=1.27.1)
Requires-Dist: setuptools
